pynadlan/__init__.py
pynadlan/api.py
pynadlan/locations.py
pynadlan-0.2.0.dist-info/METADATA
pynadlan-0.2.0.dist-info/WHEEL
pynadlan-0.2.0.dist-info/top_level.txt
pynadlan-0.2.0.dist-info/RECORD
